hwtBuildsystem/__init__.py
hwtBuildsystem/fileUtils.py
hwtBuildsystem/common/__init__.py
hwtBuildsystem/common/cmdResult.py
hwtBuildsystem/common/executor.py
hwtBuildsystem/common/project.py
hwtBuildsystem/common/tcl.py
hwtBuildsystem/examples/__init__.py
hwtBuildsystem/examples/example_units.py
hwtBuildsystem/examples/synthetizeUnit.py
hwtBuildsystem/examples/vivado/__init__.py
hwtBuildsystem/examples/vivado/createBdProject.py
hwtBuildsystem/examples/vivado/implementBd.py
hwtBuildsystem/examples/vivado/importBdTcl.py
hwtBuildsystem/examples/vivado/outputProcessing.py
hwtBuildsystem/examples/vivado/synthetizeBd.py
hwtBuildsystem/fakeTool/__init__.py
hwtBuildsystem/fakeTool/recordingExecutor.py
hwtBuildsystem/fakeTool/replayingExecutor.py
hwtBuildsystem/fakeTool/utils.py
hwtBuildsystem/ioConstraints/__init__.py
hwtBuildsystem/modelsim/__init__.py
hwtBuildsystem/modelsim/runVerification.py
hwtBuildsystem/quartus/__init__.py
hwtBuildsystem/quartus/config.py
hwtBuildsystem/quartus/executor.py
hwtBuildsystem/quartus/part.py
hwtBuildsystem/quartus/report.py
hwtBuildsystem/quartus/api/__init__.py
hwtBuildsystem/quartus/api/project.py
hwtBuildsystem/quartus/api/tcl.py
hwtBuildsystem/quartus/logParser/__init__.py
hwtBuildsystem/quartus/logParser/synthesis.py
hwtBuildsystem/vivado/__init__.py
hwtBuildsystem/vivado/config.py
hwtBuildsystem/vivado/executor.py
hwtBuildsystem/vivado/metaParser.py
hwtBuildsystem/vivado/part.py
hwtBuildsystem/vivado/report.py
hwtBuildsystem/vivado/xdcGen.py
hwtBuildsystem/vivado/api/__init__.py
hwtBuildsystem/vivado/api/boardDesign.py
hwtBuildsystem/vivado/api/net.py
hwtBuildsystem/vivado/api/pin.py
hwtBuildsystem/vivado/api/port.py
hwtBuildsystem/vivado/api/project.py
hwtBuildsystem/vivado/api/tcl.py
hwtBuildsystem/vivado/api/unit.py
hwtBuildsystem/vivado/logParser/__init__.py
hwtBuildsystem/vivado/logParser/synthesis.py
hwtBuildsystem/yosys/__init__.py
hwtBuildsystem/yosys/config.py
hwtBuildsystem/yosys/executor.py
hwtBuildsystem/yosys/part.py
hwtBuildsystem-0.1.dist-info/LICENSE
hwtBuildsystem-0.1.dist-info/METADATA
hwtBuildsystem-0.1.dist-info/WHEEL
hwtBuildsystem-0.1.dist-info/top_level.txt
hwtBuildsystem-0.1.dist-info/RECORD
